fcgi_client/FastCGIClient.py
fcgi_client/PHPFPMClient.py
fcgi_client/__init__.py
fcgi_client-0.0.1.dist-info/METADATA
fcgi_client-0.0.1.dist-info/WHEEL
fcgi_client-0.0.1.dist-info/licenses/LICENSE
fcgi_client-0.0.1.dist-info/RECORD
