Metadata-Version: 2.1
Name: fcgi_client
Version: 0.0.1
Summary: FastCGI Python3 client
Project-URL: Homepage, https://github.com/darkpills/fcgi-client
Project-URL: Issues, https://github.com/darkpills/fcgi-client/issues
Author: darkpills
License-File: LICENSE
Classifier: License :: OSI Approved :: MIT License
Classifier: Operating System :: OS Independent
Classifier: Programming Language :: Python :: 3
Requires-Python: >=3.8
